hamilflow/__init__.py
hamilflow/models/__init__.py
hamilflow/models/harmonic_oscillator.py
hamilflow-0.0.0.dist-info/LICENSE
hamilflow-0.0.0.dist-info/METADATA
hamilflow-0.0.0.dist-info/WHEEL
hamilflow-0.0.0.dist-info/RECORD
