Metadata-Version: 2.1
Name: hamilflow
Version: 0.0.0
Summary: Dataset of simple physical systems.
License: MIT
Author: LM
Author-email: hi@leima.is
Requires-Python: >=3.9,<3.13
Classifier: License :: OSI Approved :: MIT License
Classifier: Programming Language :: Python :: 3
Classifier: Programming Language :: Python :: 3.9
Classifier: Programming Language :: Python :: 3.10
Classifier: Programming Language :: Python :: 3.11
Requires-Dist: loguru (>=0.7.2,<0.8.0)
Requires-Dist: matplotlib (>=3.8.3,<4.0.0)
Requires-Dist: numpy (>=1.26.3,<2.0.0)
Requires-Dist: pandas (>=2.0.0,<=2.2.0)
Requires-Dist: pydantic (>=2.6.1,<3.0.0)
